{
    "replace": false,
    "values": [
        {
            "id": "reclaimed:aspect/dragonkin/wings",
            "required": false
        },
        {
            "id": "reclaimed:aspect/phoenix/wings",
            "required": false
        },
        {
            "id": "reclaimed:aspect/morphling/form/aquatic",
            "required": false
        },
        {
            "id": "reclaimed:aspect/morphling/form/fire",
            "required": false
        },
        {
            "id": "reclaimed:aspect/morphling/form/void",
            "required": false
        },
        {
            "id": "reclaimed:aspect/morphling/form/switching_effects",
            "required": false
        },
        {
            "id": "reclaimed:focus/remnant/save",
            "required": false
        },
        {
            "id": "reclaimed:focus/remnant/teleport",
            "required": false
        },
        {
            "id": "reclaimed:focus/frostling/upgrade_ice",
            "required": false
        },
        {
            "id": "reclaimed:focus/phoenix/use",
            "required": false
        },
        {
            "id": "reclaimed:focus/voidborne/change_index",
            "required": false
        },
        {
            "id": "reclaimed:focus/voidborne/check_index",
            "required": false
        },
        {
            "id": "reclaimed:focus/voidborne/store_entity",
            "required": false
        },
        {
            "id": "reclaimed:focus/voidborne/summon_all",
            "required": false
        },
        {
            "id": "reclaimed:focus/voidborne/summon_index",
            "required": false
        },
        {
            "id": "reclaimed:focus/morphling/modify_offhand",
            "required": false
        },
        {
            "id": "reclaimed:focus/morphling/use_mainhand",
            "required": false
        }
    ]
}